QATRADER/__init__.py
QATRADER/setting.py
QATRADER/trader.py
QATRADER/util.py
QATRADER/webhandler.py
QATRADER-1.5.dist-info/METADATA
QATRADER-1.5.dist-info/RECORD
QATRADER-1.5.dist-info/WHEEL
QATRADER-1.5.dist-info/entry_points.txt
QATRADER-1.5.dist-info/top_level.txt
QATRADER-1.5.dist-info/zip-safe
