Metadata-Version: 2.1
Name: QATRADER
Version: 1.5
Summary: QUANTAXIS TRADER
Home-page: https://github.com/yutiansut/QATRADER
Author: yutiansut
Author-email: yutiansut@qq.com
License: MIT
Keywords: quantaxis,quant,finance,Backtest,Framework
Platform: UNKNOWN
Classifier: License :: OSI Approved :: MIT License
Classifier: Programming Language :: Python
Classifier: Intended Audience :: Developers
Classifier: Operating System :: OS Independent
Requires-Dist: pika
Requires-Dist: quantaxis (>=1.5.29)
Requires-Dist: quantaxis-webserver
Requires-Dist: quantaxis-pubsub
Requires-Dist: quantaxis-otgbroker (>=1.9.2)
Requires-Dist: qaenv
